flaskr/__init__.py
flaskr/auth.py
flaskr/blog.py
flaskr/db.py
flaskr/requirments.txt
flaskr/schema.sql
flaskr/static/style.css
flaskr/templates/base.html
flaskr/templates/auth/login.html
flaskr/templates/auth/register.html
flaskr/templates/blog/create.html
flaskr/templates/blog/index.html
flaskr/templates/blog/update.html
flaskr_test-1.0.1.dist-info/METADATA
flaskr_test-1.0.1.dist-info/WHEEL
flaskr_test-1.0.1.dist-info/top_level.txt
flaskr_test-1.0.1.dist-info/RECORD
